tradetestlib/__init__.py
tradetestlib/evaluation.py
tradetestlib/mt5_data.py
tradetestlib/optimize.py
tradetestlib/simulation.py
tradetestlib-1.2.0.dist-info/LICENSE
tradetestlib-1.2.0.dist-info/METADATA
tradetestlib-1.2.0.dist-info/WHEEL
tradetestlib-1.2.0.dist-info/top_level.txt
tradetestlib-1.2.0.dist-info/RECORD
