Metadata-Version: 2.1
Name: tradetestlib
Version: 1.2.0
Summary: A backtesting library for MetaTrader5
Home-page: https://github.com/alfarasjb/TradeTestLib
Author: Jay Alfaras
Author-email: alfarasjb@gmail.com
License: MIT
Requires-Python: >=3.8
License-File: LICENSE
Requires-Dist: numpy >=1.26.0
Requires-Dist: pandas >=2.0.0
Requires-Dist: matplotlib >=3.5.2
Requires-Dist: seaborn >=0.11.2
Requires-Dist: tqdm >=4.64.1
Requires-Dist: MetaTrader5 >=5.0.45
